rest_adapter.py
rest_adapter-0.1.3.dist-info/licenses/LICENSE
rest_adapter-0.1.3.dist-info/METADATA
rest_adapter-0.1.3.dist-info/WHEEL
rest_adapter-0.1.3.dist-info/top_level.txt
rest_adapter-0.1.3.dist-info/RECORD
