Metadata-Version: 2.4
Name: rest_adapter
Version: 0.1.3
Summary: A reusable REST API adapter built on top of the popular requests library.
Author-email: HBNet Networks <dev@hbnet.tech>
License-Expression: GPL-3.0-or-later
Project-URL: Homepage, https://github.com/HNBetNetworks/rest-adapter
Project-URL: Repository, https://github.com/HNBetNetworks/rest-adapter
Project-URL: Issues, https://github.com/HNBetNetworks/rest-adapter/issues
Requires-Python: >=3.10
License-File: LICENSE
Requires-Dist: requests>=2.32.4
Dynamic: license-file
